pycld2/__init__.py
pycld2/_pycld2.cpython-311-darwin.so
pycld2_chatbees_fork-0.42.dist-info/LICENSE
pycld2_chatbees_fork-0.42.dist-info/METADATA
pycld2_chatbees_fork-0.42.dist-info/WHEEL
pycld2_chatbees_fork-0.42.dist-info/top_level.txt
pycld2_chatbees_fork-0.42.dist-info/RECORD
